similarity/__init__.py
similaritytext-0.3.1.dist-info/licenses/LICENSE
similaritytext-0.3.1.dist-info/METADATA
similaritytext-0.3.1.dist-info/WHEEL
similaritytext-0.3.1.dist-info/top_level.txt
similaritytext-0.3.1.dist-info/RECORD
