Metadata-Version: 2.4
Name: similaritytext
Version: 0.3.1
Summary: Advanced text similarity and classification using AI and Machine Learning
Home-page: https://github.com/fabiocax/SimilarityText
Author: Fabio Alberti
Author-email: fabiocax@gmail.com
License: MIT
Project-URL: Bug Reports, https://github.com/fabiocax/SimilarityText/issues
Project-URL: Source, https://github.com/fabiocax/SimilarityText
Project-URL: Documentation, https://github.com/fabiocax/SimilarityText/blob/main/README.md
Project-URL: Changelog, https://github.com/fabiocax/SimilarityText/blob/main/CHANGELOG.md
Keywords: nlp,natural language processing,text similarity,semantic similarity,text classification,machine learning,deep learning,transformers,bert,sentence transformers,tf-idf,cosine similarity,sentiment analysis,multilingual,ai,artificial intelligence
Classifier: Development Status :: 4 - Beta
Classifier: Intended Audience :: Developers
Classifier: Intended Audience :: Science/Research
Classifier: Intended Audience :: Education
Classifier: Topic :: Scientific/Engineering :: Artificial Intelligence
Classifier: Topic :: Text Processing :: Linguistic
Classifier: Topic :: Software Development :: Libraries :: Python Modules
Classifier: License :: OSI Approved :: MIT License
Classifier: Programming Language :: Python :: 3
Classifier: Programming Language :: Python :: 3.7
Classifier: Programming Language :: Python :: 3.8
Classifier: Programming Language :: Python :: 3.9
Classifier: Programming Language :: Python :: 3.10
Classifier: Programming Language :: Python :: 3.11
Classifier: Programming Language :: Python :: 3.12
Classifier: Operating System :: OS Independent
Classifier: Natural Language :: English
Classifier: Natural Language :: Portuguese
Classifier: Natural Language :: Spanish
Classifier: Natural Language :: French
Classifier: Natural Language :: German
Classifier: Framework :: Jupyter
Requires-Python: >=3.7
License-File: LICENSE
Requires-Dist: click
Requires-Dist: joblib
Requires-Dist: nltk
Requires-Dist: regex
Requires-Dist: scikit-learn
Requires-Dist: scipy
Requires-Dist: threadpoolctl
Requires-Dist: tqdm
Requires-Dist: langdetect
Requires-Dist: numpy
Provides-Extra: transformers
Requires-Dist: sentence-transformers>=2.0.0; extra == "transformers"
Requires-Dist: torch>=1.9.0; extra == "transformers"
Requires-Dist: transformers>=4.0.0; extra == "transformers"
Provides-Extra: dev
Requires-Dist: pytest>=6.0; extra == "dev"
Requires-Dist: pytest-cov>=2.0; extra == "dev"
Requires-Dist: black>=21.0; extra == "dev"
Requires-Dist: flake8>=3.9; extra == "dev"
Requires-Dist: mypy>=0.900; extra == "dev"
Dynamic: author
Dynamic: author-email
Dynamic: classifier
Dynamic: description
Dynamic: description-content-type
Dynamic: home-page
Dynamic: keywords
Dynamic: license
Dynamic: license-file
Dynamic: project-url
Dynamic: provides-extra
Dynamic: requires-dist
Dynamic: requires-python
Dynamic: summary
